<?xml version="1.0" standalone="no"?>
<!DOCTYPE TWaD_unit_info_card_abilities_strings>
<root>
  <edit_uuid>daa514b4-4fdc-11e0-8001-6cf049ef02b0</edit_uuid>
  <field>
    <primary_key>1</primary_key>
    <name>key</name>
    <field_type>text</field_type>
    <required>0</required>
    <max_length>50</max_length>
  </field>
  <field>
    <primary_key>0</primary_key>
    <name>bullet_text</name>
    <field_type>text</field_type>
    <required>0</required>
    <max_length>2048</max_length>
  </field>
  <field>
    <primary_key>0</primary_key>
    <name>tooltip_text</name>
    <field_type>text</field_type>
    <required>0</required>
    <max_length>2048</max_length>
  </field>
</root>
