<?xml version="1.0" encoding="UTF-8" standalone="no"?>
<!DOCTYPE TWaD_cai_personalities_faction_junctions>
<root>
<edit_uuid>70a6c1b9-bdb6-4519-b9a1-d95ce5af3ef1</edit_uuid>
<field>
<field_uuid>{8030eecf-d3f8-4aaf-9c8b-80c31ce02daa}</field_uuid>
<primary_key>1</primary_key>
<name>faction_key</name>
<field_type>text</field_type>
<required>1</required>
<max_length>255</max_length>
<column_source_column>key</column_source_column>
<column_source_table>factions</column_source_table>
</field>
<field>
<field_uuid>{f7d16958-c49a-4d5a-ae6d-abffa30cb391}</field_uuid>
<primary_key>1</primary_key>
<name>campaign_key</name>
<field_type>text</field_type>
<required>1</required>
<max_length>50</max_length>
<column_source_column>campaign_name</column_source_column>
<column_source_table>campaigns</column_source_table>
</field>
<field>
<field_uuid>{81a38638-f033-4dbc-b2c3-9ff64bad40a2}</field_uuid>
<primary_key>0</primary_key>
<name>default_personality</name>
<field_type>text</field_type>
<required>1</required>
<max_length>255</max_length>
<column_source_column>key</column_source_column>
<column_source_table>cai_personalities</column_source_table>
</field>
<field>
<field_uuid>{fc2f2966-5999-4f95-b9a1-8ad19e0ab425}</field_uuid>
<primary_key>0</primary_key>
<name>personality_group</name>
<field_type>text</field_type>
<required>1</required>
<max_length>2000</max_length>
<column_source_column>random_personality_group_key</column_source_column>
<column_source_table>cai_personalities_random_groups</column_source_table>
</field>
<field>
<field_uuid>{57ff91e3-d8d8-4fe7-b4fe-ced4723cf74b}</field_uuid>
<primary_key>0</primary_key>
<name>randomisation_policy_key</name>
<field_type>text</field_type>
<required>1</required>
<max_length>2000</max_length>
<column_source_column>randomisation_policy_key</column_source_column>
<column_source_table>cai_personalities_randomisation_policies</column_source_table>
</field>
</root>
